mullai/__init__.py
mullai/mullai.py
mullai/core/__init__.py
mullai/core/copytree.py
mullai/core/io.py
mullai/core/loader.py
mullai/generator/__init__.py
mullai/generator/json_parser.py
mullai/generator/mysql.py
mullai/generator/posts.py
mullai/libs/__init__.py
mullai/libs/argparse.py
mullai/util/__init__.py
mullai/util/colorify.py
mullai/util/ext.py
mullai/util/formatter.py
mullai/util/log.py
mullai/util/system.py
mullai-1.0.3.dist-info/LICENSE.txt
mullai-1.0.3.dist-info/METADATA
mullai-1.0.3.dist-info/WHEEL
mullai-1.0.3.dist-info/entry_points.txt
mullai-1.0.3.dist-info/top_level.txt
mullai-1.0.3.dist-info/RECORD
